rcwa/__init__.py
rcwa/context.py
rcwa/docs/Makefile
rcwa/docs/api.rst
rcwa/docs/conf.py
rcwa/docs/index.rst
rcwa/docs/make.bat
rcwa/examples/bragg_mirror.py
rcwa/examples/context.py
rcwa/examples/triangleData.csv
rcwa/examples/triangular_photonic_crystal.py
rcwa/netlist/netlist_parser.py
rcwa/netlist/sample_netlist.txt
rcwa/nkData/AlN_Pastrnak-o.csv
rcwa/nkData/Al_McPeak.csv
rcwa/nkData/ITO_Konig.csv
rcwa/nkData/Si3N4_Luke.csv
rcwa/nkData/SiO2_Lemarchand.csv
rcwa/nkData/Si_Schinke.csv
rcwa/source/context.py
rcwa/source/crystal.py
rcwa/source/fresnel.py
rcwa/source/harmonics.py
rcwa/source/layer.py
rcwa/source/material.py
rcwa/source/matrices.py
rcwa/source/matrixParser.py
rcwa/source/plotter.py
rcwa/source/shorthand.py
rcwa/source/solver.py
rcwa/source/source.py
rcwa/test/__init__.py
rcwa/test/context.py
rcwa/test/fastRunner.py
rcwa/test/fullRunner.py
rcwa/test/generateMoreData.py
rcwa/test/shorthandTest.py
rcwa/test/testCrystal.py
rcwa/test/testHarmonics.py
rcwa/test/testLayer.py
rcwa/test/testMaterial.py
rcwa/test/testMatrices1x1Harmonics.py
rcwa/test/testMatrices3x3Harmonics.py
rcwa/test/testNetlistParser.py
rcwa/test/testSolver1x1Harmonics.py
rcwa/test/testSolver3x3Harmonics.py
rcwa/test/testSource.py
rcwa/test/triangleData.csv
rcwa/test/matrixDataNormal/SGlobal11.txt
rcwa/test/matrixDataNormal/SGlobal12.txt
rcwa/test/matrixDataNormal/SGlobal21.txt
rcwa/test/matrixDataNormal/SGlobal22.txt
rcwa/test/matrixDataNormal/freeSpace/KzFreeSpace.txt
rcwa/test/matrixDataNormal/freeSpace/LamFreeSpace.txt
rcwa/test/matrixDataNormal/freeSpace/QFreeSpace.txt
rcwa/test/matrixDataNormal/freeSpace/VFreeSpace.txt
rcwa/test/matrixDataNormal/layer1/ALayer1.txt
rcwa/test/matrixDataNormal/layer1/BLayer1.txt
rcwa/test/matrixDataNormal/layer1/LambdaLayer1.txt
rcwa/test/matrixDataNormal/layer1/OmegaSquaredLayer1.txt
rcwa/test/matrixDataNormal/layer1/PLayer1.txt
rcwa/test/matrixDataNormal/layer1/QLayer1.txt
rcwa/test/matrixDataNormal/layer1/S11Layer1.txt
rcwa-0.1.55.dist-info/LICENSE.txt
rcwa-0.1.55.dist-info/METADATA
rcwa-0.1.55.dist-info/WHEEL
rcwa-0.1.55.dist-info/top_level.txt
rcwa-0.1.55.dist-info/RECORD
