Metadata-Version: 2.1
Name: rcwa
Version: 0.1.55
Summary: Python Implementation of Rigorous Coupled Wave Analysis
Home-page: https://github.com/edmundsj/RCWA
Author: Jordan Edmunds
Author-email: jordan.e@berkeley.edu
License: MIT
Platform: UNKNOWN
Classifier: Programming Language :: Python :: 3
Classifier: License :: OSI Approved :: MIT License
Classifier: Operating System :: OS Independent
Requires-Python: >=3.6
Requires-Dist: numpy (>=1.14.5)
Requires-Dist: matplotlib (>=2.0.0)
Requires-Dist: pandas (>=0.24.0)
Requires-Dist: scipy (>=1.2.2)
